ukbeaver/__init__.py
ukbeaver/data/__init__.py
ukbeaver/data/imaging.py
ukbeaver/data/tabular.py
ukbeaver/util/__init__.py
ukbeaver/util/atlas.py
ukbeaver/util/category.py
ukbeaver/util/helper.py
ukbeaver/util/schema.py
ukbeaver-0.3.2.dist-info/licenses/LICENSE
ukbeaver-0.3.2.dist-info/METADATA
ukbeaver-0.3.2.dist-info/WHEEL
ukbeaver-0.3.2.dist-info/top_level.txt
ukbeaver-0.3.2.dist-info/RECORD
