Metadata-Version: 2.4
Name: ukbeaver
Version: 0.3.2
Summary: Add your description here
Requires-Python: >=3.12
License-File: LICENSE
Requires-Dist: polars[plot]>=1.35.1
Requires-Dist: requests>=2.32.5
Dynamic: license-file
